turboactivate/__init__.py
turboactivate/c_wrapper.py
turboactivate-4.4.4.1.dist-info/LICENSE
turboactivate-4.4.4.1.dist-info/METADATA
turboactivate-4.4.4.1.dist-info/WHEEL
turboactivate-4.4.4.1.dist-info/top_level.txt
turboactivate-4.4.4.1.dist-info/RECORD
