Metadata-Version: 2.1
Name: turboactivate
Version: 4.4.4.1
Summary: Python integration for the LimeLM TurboActivate library. This lets you add hardware-locked licensing (a.k.a. node-locked licensing) to your Python app.
Home-page: https://wyday.com/limelm/help/using-turboactivate-with-python/
Author: Develer S.r.L
Author-email: info@develer.com
Maintainer: wyDay, LLC
Maintainer-email: support@wyday.com
License: UNKNOWN
Download-URL: https://github.com/wyday/python-turboactivate
Platform: UNKNOWN
Classifier: Development Status :: 5 - Production/Stable
Classifier: Intended Audience :: Developers
Classifier: License :: OSI Approved :: MIT License
Classifier: Topic :: Software Development :: Libraries :: Python Modules
Classifier: Programming Language :: Python
Classifier: Programming Language :: Python :: 2
Classifier: Programming Language :: Python :: 3
License-File: LICENSE
